vetrr/__init__.py
vetrr/vet_redrock.py
vetrr-0.1.9.data/scripts/vetrr_vet_rr
vetrr-0.1.9.dist-info/LICENSE
vetrr-0.1.9.dist-info/METADATA
vetrr-0.1.9.dist-info/WHEEL
vetrr-0.1.9.dist-info/dependency_links.txt
vetrr-0.1.9.dist-info/top_level.txt
vetrr-0.1.9.dist-info/zip-safe
vetrr-0.1.9.dist-info/RECORD
