Metadata-Version: 2.1
Name: vetrr
Version: 0.1.9
Summary: vet redrock outputs
Home-page: http://github.com/mattcwilde/vetrr
Author: Matthew Wilde
Author-email: mattcwilde@gmail.com
License: MIT
Platform: UNKNOWN
Requires-Dist: matplotlib
Requires-Dist: pyYAML
Requires-Dist: astropy
Requires-Dist: future
Requires-Dist: numpy
